serwersms/__init__.py
serwersms/account.py
serwersms/blacklist.py
serwersms/contact.py
serwersms/error.py
serwersms/file.py
serwersms/group.py
serwersms/message.py
serwersms/payment.py
serwersms/phone.py
serwersms/premium.py
serwersms/sender.py
serwersms/serwersms.py
serwersms/stat.py
serwersms/subaccount.py
serwersms/template.py
serwersmsv2api-0.0.1.dist-info/licenses/LICENSE
serwersmsv2api-0.0.1.dist-info/METADATA
serwersmsv2api-0.0.1.dist-info/WHEEL
serwersmsv2api-0.0.1.dist-info/top_level.txt
serwersmsv2api-0.0.1.dist-info/RECORD
