Metadata-Version: 2.4
Name: serwersmsv2api
Version: 0.0.1
Summary: Python client for remote communication with SerwerSMS.pl API v2
Home-page: https://serwersms.pl
Author: SerwerSMS
Author-email: dev@serwersms.pl
Classifier: Programming Language :: Python :: 3
Classifier: License :: OSI Approved :: MIT License
Classifier: Operating System :: OS Independent
Requires-Python: >=3.9
License-File: LICENSE
Dynamic: license-file
